odoo8_addon_base_report_to_printer-8.0.0.2.0.99.dev35-py3.8-nspkg.pth
odoo_addons/base_report_to_printer/README.rst
odoo_addons/base_report_to_printer/__init__.py
odoo_addons/base_report_to_printer/__openerp__.py
odoo_addons/base_report_to_printer/base_report_to_printer.xml
odoo_addons/base_report_to_printer/ir_report.py
odoo_addons/base_report_to_printer/printing.py
odoo_addons/base_report_to_printer/printing_data.xml
odoo_addons/base_report_to_printer/printing_view.xml
odoo_addons/base_report_to_printer/report.py
odoo_addons/base_report_to_printer/report_service.py
odoo_addons/base_report_to_printer/report_xml_action.py
odoo_addons/base_report_to_printer/users.py
odoo_addons/base_report_to_printer/i18n/am.po
odoo_addons/base_report_to_printer/i18n/ar.po
odoo_addons/base_report_to_printer/i18n/base_report_to_printer.pot
odoo_addons/base_report_to_printer/i18n/bg.po
odoo_addons/base_report_to_printer/i18n/bs.po
odoo_addons/base_report_to_printer/i18n/ca.po
odoo_addons/base_report_to_printer/i18n/ca_ES.po
odoo_addons/base_report_to_printer/i18n/cs.po
odoo_addons/base_report_to_printer/i18n/da.po
odoo_addons/base_report_to_printer/i18n/da_DK.po
odoo_addons/base_report_to_printer/i18n/de.po
odoo_addons/base_report_to_printer/i18n/el_GR.po
odoo_addons/base_report_to_printer/i18n/en_AU.po
odoo_addons/base_report_to_printer/i18n/en_GB.po
odoo_addons/base_report_to_printer/i18n/es.po
odoo_addons/base_report_to_printer/i18n/es_AR.po
odoo_addons/base_report_to_printer/i18n/es_CL.po
odoo_addons/base_report_to_printer/i18n/es_CO.po
odoo_addons/base_report_to_printer/i18n/es_CR.po
odoo_addons/base_report_to_printer/i18n/es_DO.po
odoo_addons/base_report_to_printer/i18n/es_EC.po
odoo_addons/base_report_to_printer/i18n/es_ES.po
odoo_addons/base_report_to_printer/i18n/es_MX.po
odoo_addons/base_report_to_printer/i18n/es_PE.po
odoo_addons/base_report_to_printer/i18n/es_PY.po
odoo_addons/base_report_to_printer/i18n/es_VE.po
odoo_addons/base_report_to_printer/i18n/et.po
odoo8_addon_base_report_to_printer-8.0.0.2.0.99.dev35.dist-info/METADATA
odoo8_addon_base_report_to_printer-8.0.0.2.0.99.dev35.dist-info/WHEEL
odoo8_addon_base_report_to_printer-8.0.0.2.0.99.dev35.dist-info/namespace_packages.txt
odoo8_addon_base_report_to_printer-8.0.0.2.0.99.dev35.dist-info/top_level.txt
odoo8_addon_base_report_to_printer-8.0.0.2.0.99.dev35.dist-info/RECORD
